neo4j_utils/__init__.py
neo4j_utils/_driver.py
neo4j_utils/_logger.py
neo4j_utils/_metadata.py
neo4j_utils/_misc.py
neo4j_utils/_n4jversion.py
neo4j_utils/_print.py
neo4j_utils/_query.py
neo4j_utils-0.0.12.dist-info/LICENSE
neo4j_utils-0.0.12.dist-info/METADATA
neo4j_utils-0.0.12.dist-info/WHEEL
neo4j_utils-0.0.12.dist-info/RECORD
