Metadata-Version: 2.1
Name: neo4j-utils
Version: 0.0.12
Summary: Little extra convenience in managing Neo4j access
Home-page: https://github.com/saezlab/neo4j-utils
License: MIT
Author: Denes Turei
Author-email: turei.denes@gmail.com
Requires-Python: >=3.8,<4.0
Classifier: Development Status :: 2 - Pre-Alpha
Classifier: Intended Audience :: Developers
Classifier: Intended Audience :: Science/Research
Classifier: License :: OSI Approved :: GNU General Public License v3 (GPLv3)
Classifier: License :: OSI Approved :: MIT License
Classifier: Natural Language :: English
Classifier: Operating System :: OS Independent
Classifier: Programming Language :: Python
Classifier: Programming Language :: Python :: 3
Classifier: Programming Language :: Python :: 3.8
Classifier: Programming Language :: Python :: 3.9
Classifier: Programming Language :: Python :: 3.10
Classifier: Programming Language :: Python :: 3.11
Classifier: Programming Language :: Python :: 3.12
Classifier: Topic :: Scientific/Engineering :: Bio-Informatics
Requires-Dist: PyYAML (>=5.0)
Requires-Dist: appdirs (>=1.4.4)
Requires-Dist: colorlog
Requires-Dist: neo4j (>=4.4,<5.0)
Requires-Dist: toml
Project-URL: Bug Tracker, https://github.com/saezlab/neo4j-utils/issues
Project-URL: Repository, https://github.com/saezlab/neo4j-utils
